kick_chat/client.py
kick_chat/constants.py
kick_chat/main.py
kick_chat/utils.py
kick_chat-1.0.0.dist-info/LICENSE
kick_chat-1.0.0.dist-info/METADATA
kick_chat-1.0.0.dist-info/WHEEL
kick_chat-1.0.0.dist-info/entry_points.txt
kick_chat-1.0.0.dist-info/top_level.txt
kick_chat-1.0.0.dist-info/RECORD
