Metadata-Version: 2.1
Name: kick-chat
Version: 1.0.0
Summary: kick.com chat in the terminal
Author: Piotr Skowroński
License: GPLv3
Classifier: Environment :: Console
Classifier: Programming Language :: Python :: 3
Classifier: License :: OSI Approved :: GNU General Public License v3 (GPLv3)
Requires-Python: >=3.10
License-File: LICENSE
Requires-Dist: cffi (==1.15.1)
Requires-Dist: curl-cffi (==0.5.7)
Requires-Dist: pycparser (==2.21)
Requires-Dist: python-dateutil (==2.8.2)
Requires-Dist: rel (==0.4.9)
Requires-Dist: six (==1.16.0)
Requires-Dist: websocket-client (==1.6.1)
